{
	"id":"8",
	"begin":
		{
			"name": "Los Tuzos",
			"icon": "assets/img/alimentadoras_icons/8.png",
			"latitude":20.05272,
			"longitude": -98.75659
		},
	"end":
		{
			"name": "Centro de Justicia",
			"icon": "assets/img/estaciones_icons/centroDeJusticia.png",
			"latitude":20.06005, 
			"longitude":-98.78417
		},
	"paradas":
		[
			{"longitude":-98.7823141,
			"latitude":20.0590252},
			{"longitude":-98.7802756,
			"latitude":20.0579721},
			{"longitude":-98.781504,
			"latitude":20.055387},
			{"longitude":-98.782357,
			"latitude":20.0554828},
			{"longitude":-98.7792778,
			"latitude":20.0562286},
			{"longitude":-98.7761785,
			"latitude":20.0593477},
			{"longitude":-98.7743586,
			"latitude":20.0608846},
			{"longitude":-98.7729572,
			"latitude":20.0601615},
			{"longitude":-98.7716429,
			"latitude":20.060547},
			{"longitude":-98.7699088,
			"latitude":20.0602346},
			{"longitude":-98.7682567,
			"latitude":20.0598743},
			{"longitude":-98.7663897,
			"latitude":20.0594787},
			{"longitude":-98.7643392,
			"latitude":20.0590303},
			{"longitude":-98.7631523,
			"latitude":20.0587657},
			{"longitude":-98.7633776,
			"latitude":20.0575689},
			{"longitude":-98.7638873,
			"latitude":20.0556088},
			{"longitude":-98.7637424,
			"latitude":20.0551804},
			{"longitude":-98.7631202,
			"latitude":20.0575337},
			{"longitude":-98.7631215,
			"latitude":20.0589661},
			{"longitude":-98.764295,
			"latitude":20.0592419},
			{"longitude":-98.7715396,
			"latitude":20.060804},
			{"longitude":-98.7694328,
			"latitude":20.0603354},
			{"longitude":-98.7678046,
			"latitude":20.0599738},
			{"longitude":-98.7661538,
			"latitude":20.0596224},
			{"longitude":-98.7643969,
			"latitude":20.0540114},
			{"longitude":-98.7641072,
			"latitude":20.0540819},
			{"longitude":-98.7647939,
			"latitude":20.0528725},
			{"longitude":-98.764515,
			"latitude":20.0527226},
			{"longitude":-98.7628386,
			"latitude":20.0519478},
			{"longitude":-98.7622511,
			"latitude":20.0517878},
			{"longitude":-98.7609208,
			"latitude":20.0511289},
			{"longitude":-98.760843,
			"latitude":20.0512763},
			{"longitude":-98.7604889,
			"latitude":20.052225},
			{"longitude":-98.7604715,
			"latitude":20.0523207},
			{"longitude":-98.7599552,
			"latitude":20.0520889},
			{"longitude":-98.760041,
			"latitude":20.0521972},
			{"longitude":-98.7587703,
			"latitude":20.0517557},
			{"longitude":-98.758488,
			"latitude":20.0520965},
			{"longitude":-98.7580669,
			"latitude":20.0532107},
			{"longitude":-98.7570544,
			"latitude":20.0516794}
		],
	"ruta_ida":
		[
			{"longitude":-98.75664,
			"latitude":20.0526608},
			{"longitude":-98.7570369,
			"latitude":20.0515925},
			{"longitude":-98.7585819,
			"latitude":20.052036},
			{"longitude":-98.7586623,
			"latitude":20.0517739},
			{"longitude":-98.7606096,
			"latitude":20.0523283},
			{"longitude":-98.7608564,
			"latitude":20.0511692},
			{"longitude":-98.7645954,
			"latitude":20.0527213},
			{"longitude":-98.7642092,
			"latitude":20.0539106},
			{"longitude":-98.763501,
			"latitude":20.0561228},
			{"longitude":-98.7628627,
			"latitude":20.058864},
			{"longitude":-98.7697881,
			"latitude":20.0603505},
			{"longitude":-98.7716603,
			"latitude":20.0607839},
			{"longitude":-98.7721539,
			"latitude":20.0608393},
			{"longitude":-98.7728244,
			"latitude":20.0609905},
			{"longitude":-98.773098,
			"latitude":20.0609854},
			{"longitude":-98.7741655,
			"latitude":20.0612222},
			{"longitude":-98.7745839,
			"latitude":20.0612525},
			{"longitude":-98.7749004,
			"latitude":20.0612122},
			{"longitude":-98.7750453,
			"latitude":20.0611467},
			{"longitude":-98.777352,
			"latitude":20.0586524},
			{"longitude":-98.7785912,
			"latitude":20.057312},
			{"longitude":-98.7804043,
			"latitude":20.0553669},
			{"longitude":-98.7807155,
			"latitude":20.0551603},
			{"longitude":-98.781091,
			"latitude":20.05513},
			{"longitude":-98.7813592,
			"latitude":20.0552359},
			{"longitude":-98.7830168,
			"latitude":20.056153},
			{"longitude":-98.7840521,
			"latitude":20.0567627},
			{"longitude":-98.7840736,
			"latitude":20.0571961},
			{"longitude":-98.7841487,
			"latitude":20.0574178},
			{"longitude":-98.7842667,
			"latitude":20.0575438},
			{"longitude":-98.7848622,
			"latitude":20.0578663},
			{"longitude":-98.7851787,
			"latitude":20.0580124},
			{"longitude":-98.7852645,
			"latitude":20.0581182},
			{"longitude":-98.7852752,
			"latitude":20.0583097},
			{"longitude":-98.7846315,
			"latitude":20.059504},
			{"longitude":-98.7845296,
			"latitude":20.0595644},
			{"longitude":-98.7842292,
			"latitude":20.0601288}
		],
	"ruta_vuelta":
		[
			{"longitude":-98.7841702,
			"latitude":20.0601237},
			{"longitude":-98.778854,
			"latitude":20.0573044},
			{"longitude":-98.7787816,
			"latitude":20.0570953},
			{"longitude":-98.7801039,
			"latitude":20.0556894},
			{"longitude":-98.7804043,
			"latitude":20.0553669},
			{"longitude":-98.7806189,
			"latitude":20.0552258},
			{"longitude":-98.7808871,
			"latitude":20.0551351},
			{"longitude":-98.7811553,
			"latitude":20.0551552},
			{"longitude":-98.7826037,
			"latitude":20.055891},
			{"longitude":-98.782711,
			"latitude":20.0557196},
			{"longitude":-98.7815201,
			"latitude":20.0550746},
			{"longitude":-98.7813592,
			"latitude":20.0550847},
			{"longitude":-98.781091,
			"latitude":20.0550041},
			{"longitude":-98.7808335,
			"latitude":20.0550343},
			{"longitude":-98.7805653,
			"latitude":20.055125},
			{"longitude":-98.780297,
			"latitude":20.0552963},
			{"longitude":-98.7799644,
			"latitude":20.0555886},
			{"longitude":-98.7775505,
			"latitude":20.0581585},
			{"longitude":-98.7773252,
			"latitude":20.0582694},
			{"longitude":-98.7759114,
			"latitude":20.0596813},
			{"longitude":-98.7752058,
			"latitude":20.0604124},
			{"longitude":-98.7746089,
			"latitude":20.0611017},
			{"longitude":-98.7745364,
			"latitude":20.0611133},
			{"longitude":-98.7744879,
			"latitude":20.0610373},
			{"longitude":-98.7743804,
			"latitude":20.0609763},
			{"longitude":-98.7728512,
			"latitude":20.060154},
			{"longitude":-98.7723577,
			"latitude":20.0599524},
			{"longitude":-98.7721002,
			"latitude":20.0598516},
			{"longitude":-98.7719822,
			"latitude":20.0599323},
			{"longitude":-98.7716442,
			"latitude":20.0606503},
			{"longitude":-98.7630599,
			"latitude":20.058791},
			{"longitude":-98.7636847,
			"latitude":20.0561467},
			{"longitude":-98.7641173,
			"latitude":20.0547464},
			{"longitude":-98.7646008,
			"latitude":20.0533512},
			{"longitude":-98.7648072,
			"latitude":20.0527717},
			{"longitude":-98.7608242,
			"latitude":20.0511239},
			{"longitude":-98.760556,
			"latitude":20.0522779},
			{"longitude":-98.7586355,
			"latitude":20.0517286},
			{"longitude":-98.7581205,
			"latitude":20.0532612},
			{"longitude":-98.7567258,
			"latitude":20.0528171}
		]
}